ktg2/__init__.py
ktg2/telegram.py
ktg2/models/__init__.py
ktg2/models/chat.py
ktg2/models/message.py
ktg2/models/user.py
ktg2/models/enums/__init__.py
ktg2/models/enums/chat_type.py
ktg2/models/enums/parse_mode.py
ktg2-0.0.3.dist-info/LICENSE
ktg2-0.0.3.dist-info/METADATA
ktg2-0.0.3.dist-info/WHEEL
ktg2-0.0.3.dist-info/top_level.txt
ktg2-0.0.3.dist-info/RECORD
